scimon/__init__.py
scimon/__main__.py
scimon/cli.py
scimon/commandhook.sh
scimon/db.py
scimon/models.py
scimon/scimon.py
scimon/utils.py
scimon-0.1.1.dist-info/METADATA
scimon-0.1.1.dist-info/WHEEL
scimon-0.1.1.dist-info/entry_points.txt
scimon-0.1.1.dist-info/RECORD
