Metadata-Version: 2.4
Name: scimon
Version: 0.1.1
Summary: A scientific reproducibility tool supporting existing workflows
Project-URL: Homepage, https://github.com/Jerr-z/scimon
Project-URL: Issues, https://github.com/Jerr-z/scimon/issues
License-Expression: MIT
Classifier: Operating System :: OS Independent
Classifier: Programming Language :: Python :: 3
Requires-Python: >=3.9
Requires-Dist: graphviz>=0.20.3
Requires-Dist: jinja2>=3.1.6
Requires-Dist: pytest>=8.4.1
Requires-Dist: typer>=0.16.0
